markitdown_mcp_server/__init__.py
markitdown_mcp_server/server.py
mseep_markitdown_mcp_server-0.1.4.dist-info/licenses/LICENSE
mseep_markitdown_mcp_server-0.1.4.dist-info/METADATA
mseep_markitdown_mcp_server-0.1.4.dist-info/WHEEL
mseep_markitdown_mcp_server-0.1.4.dist-info/entry_points.txt
mseep_markitdown_mcp_server-0.1.4.dist-info/top_level.txt
mseep_markitdown_mcp_server-0.1.4.dist-info/RECORD
